Metadata-Version: 2.1
Name: autora-experimentalist-uncertainty
Version: 2.1.0
Summary: Experimentalist based on where the model is least certain.
Author-email: "Built by Sebastian Musslick, restructured by Chad Williams" <sebastian_musslick@brown.edu>
License: MIT License
Project-URL: homepage, http://www.empiricalresearch.ai
Project-URL: repository, https://github.com/AutoResearch/autora-experimentalist-uncertainty
Project-URL: documentation, https://autoresearch.github.io/autora/
Requires-Python: <4,>=3.8
License-File: LICENSE
Requires-Dist: autora-core >=3.1.0
Requires-Dist: scikit-learn
Provides-Extra: dev
Requires-Dist: autora-core[dev] ; extra == 'dev'
